jsonjsc/__init__.py
jsonjsc/decoder.py
jsonjsc/parser.py
jsonjsc-1.2.0.dist-info/METADATA
jsonjsc-1.2.0.dist-info/WHEEL
jsonjsc-1.2.0.dist-info/licenses/LICENSE
jsonjsc-1.2.0.dist-info/RECORD
