Metadata-Version: 2.1
Name: jsonjsc
Version: 1.2.0
Summary: A package to parse out C/JS style block and single line comments from JSON files.
Project-URL: Homepage, https://github.com/IDI-Systems/jsonjsc
Project-URL: Bug Tracker, https://github.com/IDI-Systems/jsonjsc
Author-email: IDI-Systems <contact@idi-systems.com>, "C. Foster" <korewananda@gmail.com>
License-File: LICENSE
Classifier: Development Status :: 5 - Production/Stable
Classifier: Intended Audience :: Developers
Classifier: License :: OSI Approved :: MIT License
Classifier: Operating System :: OS Independent
Classifier: Programming Language :: Python :: 3.7
Classifier: Programming Language :: Python :: 3.8
Classifier: Programming Language :: Python :: 3.9
Classifier: Programming Language :: Python :: 3.10
Classifier: Programming Language :: Python :: 3.11
Requires-Python: >=3.7
